pyzantium/__init__.py
pyzantium/block.py
pyzantium/chain.py
pyzantium/client.py
pyzantium/fork.py
pyzantium/node.py
pyzantium/consensus/__init__.py
pyzantium/consensus/pow.py
pyzantium/endpoint/__init__.py
pyzantium/endpoint/fastapi.py
pyzantium/endpoint/flask.py
pyzantium/storage/__init__.py
pyzantium/storage/disk.py
pyzantium-0.0.2.dist-info/LICENSE
pyzantium-0.0.2.dist-info/METADATA
pyzantium-0.0.2.dist-info/WHEEL
pyzantium-0.0.2.dist-info/entry_points.txt
pyzantium-0.0.2.dist-info/top_level.txt
pyzantium-0.0.2.dist-info/RECORD
