Metadata-Version: 2.1
Name: pyzantium
Version: 0.0.2
Summary: Python implementation and building blocks for blockchain
Home-page: https://github.com/rezamahdi/pyzantium
Author: Reza Mahdi
Author-email: rmahdi.develop@gmail.com
License: MIT
Platform: UNKNOWN
Classifier: Topic :: Security :: Cryptography
Classifier: Programming Language :: Python :: 3.8
Classifier: Topic :: Software Development :: Libraries :: Python Modules
Classifier: Development Status :: 1 - Planning
Classifier: License :: OSI Approved :: MIT License
Requires-Python: >=3.7
License-File: LICENSE
Requires-Dist: crypto
Provides-Extra: dev
Requires-Dist: pytest ; extra == 'dev'
Requires-Dist: pytest-cov ; extra == 'dev'
Requires-Dist: pytest-mock ; extra == 'dev'
Provides-Extra: doc
Requires-Dist: sphinx ; extra == 'doc'
Provides-Extra: fastapi
Requires-Dist: fastapi ; extra == 'fastapi'
